memcacheinspector/__init__.py
memcacheinspector3-0.2.3.data/scripts/mcinspect
memcacheinspector3-0.2.3.dist-info/LICENSE
memcacheinspector3-0.2.3.dist-info/METADATA
memcacheinspector3-0.2.3.dist-info/WHEEL
memcacheinspector3-0.2.3.dist-info/top_level.txt
memcacheinspector3-0.2.3.dist-info/RECORD
