Metadata-Version: 2.1
Name: memcacheinspector3
Version: 0.2.3
Summary: Memcache Inspection Module and Command-Line Utility
Home-page: https://github.com/brondsem/memcacheinspector/tree/fork
Author: Jason Simeone
Author-email: jay@classless.net
License: MIT
Keywords: memcache memcached inspector list dump export search grep keys
Platform: UNKNOWN
Classifier: Development Status :: 4 - Beta
Classifier: Environment :: Console
Classifier: Intended Audience :: Developers
Classifier: Intended Audience :: System Administrators
Classifier: Natural Language :: English
Classifier: Programming Language :: Python
Classifier: Programming Language :: Python :: 3
Classifier: Topic :: Software Development :: Libraries :: Python Modules
Classifier: License :: OSI Approved :: MIT License
Requires-Dist: python-memcached
